{"title":"一个考察王者荣耀玩家是否处于高端局的数学模型与算法","slug":"一个考察王者荣耀玩家是否处于高端局的数学模型与算法","date":"2026-04-08T15:00:41.605Z","updated":"2026-04-08T15:06:06.872Z","comments":true,"path":"api/articles/一个考察王者荣耀玩家是否处于高端局的数学模型与算法.json","excerpt":"**摘要：**   本文基于王者荣耀真实数据与正态分布模型，提出一种量化“高端局”的数学方法。通过分析巅峰赛分数分布，构建玩家超越全服比例的概率模型，得出：当赛季末巅峰分达到1549、1670、1812、2106分时，玩家分别超过95%、97.5%、99%、99.9%的对手。研究还开发Python算法，利用实时巅峰万强与第一高分动态计算当前赛季的高端局门槛（如前5%对应约1549分）。结果表明，传统“星数定段法”需转换为“分数定段法”以准确衡量对局水平，为判断高端局提供了客观标准。关键词：王者荣耀；高端局；数学模型；正态分布。","covers":["https://img.rubbish.press/file/2604/1775660622597_image.png","https://img.rubbish.press/file/2604/1775660644485_image.png"],"content":"<p>橙子.dyib(^{1*})，SLz(^{1*})，Marry a Sunset(^{1*})，Experiment in Prison(^{1*})，Big Full Stick(^{2})</p>\n<p>1 bgu.45j.632<br>\n2 bgu.45j.629<br>\n(*)3287932348@qq.com<br>\n同等贡献</p>\n<!-- 以下请在href=后的双引号里填写pdf全网链接 -->\n<a href=\"https://file.rubbish.press/artical/%E4%B8%80%E4%B8%AA%E8%80%83%E5%AF%9F%E7%8E%8B%E8%80%85%E8%8D%A3%E8%80%80%E7%8E%A9%E5%AE%B6%E6%98%AF%E5%90%A6%E5%A4%84%E4%BA%8E%E9%AB%98%E7%AB%AF%E5%B1%80%E7%9A%84%E6%95%B0%E5%AD%A6%E6%A8%A1%E5%9E%8B%E4%B8%8E%E7%AE%97%E6%B3%95.pdf?preview\" target=\"_blank\" style=\"display: inline-flex; align-items: center; gap: 8px; padding: 10px 18px; background: #2563eb; color: white; border-radius: 8px; text-decoration: none; font-size: 15px; font-weight: 500; transition: all 0.2s;\">\n  <svg style=\"width:18px;height:18px;fill:currentColor;\" viewBox=\"0 0 24 24\">\n    <path d=\"M20 2H8c-1.1 0-2 .9-2 2v12c0 1.1.9 2 2 2h12c1.1 0 2-.9 2-2V4c0-1.1-.9-2-2-2zm0 14H8V4h12v12zM4 6H2v14c0 1.1.9 2 2 2h14v-2H4V6zm12 6V9l-4 4-4-4v3h8z\"/>\n  </svg>\n  阅读 PDF 全文\n</a>\n<h2 id=\"摘要\">摘要</h2>\n<p>王者荣耀高端局的判定标准一直是玩家们津津乐道的一个话题，但是从未有人使用严谨的数学方法给出准确的判断标准。本文通过王者荣耀真实数据与正态分布模型相结合的方法，提出“星数定段法”向“分数定段法”的计算方法，构建了王者荣耀巅峰赛分数与能够达到该分数的玩家的比例关系。结果显示，当玩家的赛季末巅峰赛分数达到1549、1670、1812、2106分时，说明该玩家已经超过了王者荣耀 (95%)、(97.5%)、(99%)、(99.9%) 的玩家。并且，本研究还给出了一个能够通过实时巅峰万强与巅峰第一的分数，实时计算王者荣耀高端局对应的巅峰赛分数的Python算法。</p>\n<p><strong>关键词：</strong> 王者荣耀；高端局；数学模型；正态分布</p>\n<h2 id=\"1-引言\">1 引言</h2>\n<p>作为一款现象级国民游戏，王者荣耀各个方面均有大量玩家讨论，尤其是“英雄强度”这一问题。双方玩家通常会拿出自己的巅峰分数或者英雄战力，来表明自己对王者荣耀的理解程度，而另一方回击的方法，就是说“这根本不算高端局”等等。网上关于什么算是有含金量的高端局的讨论也层出不穷[1,2,3]。造成这一现象的重要原因，就是没有一个准确的算法指出，哪类对局算是所谓的“高端局”。因此，一个准确的用来衡量王者荣耀对局水平的数学模型迫在眉睫。</p>\n<h2 id=\"2-研究方法\">2 研究方法</h2>\n<p>本文希望构建一个模型并给出普适性算法，根据玩家王者荣耀巅峰分数以及该时段王者荣耀各分路巅峰万强等分数，来确定该玩家的对局处于什么水平。</p>\n<p><strong>表1</strong> 2026年3月29日12:30王者荣耀安卓Q区各分路排名及其对应的巅峰分数，将这些分数进行算术平均处理，得到最后一列“平均”的值</p>\n<table>\n<thead>\n<tr>\n<th>分路排名</th>\n<th>对抗路</th>\n<th>打野</th>\n<th>中路</th>\n<th>发育路</th>\n<th>游走</th>\n<th>平均</th>\n</tr>\n</thead>\n<tbody>\n<tr>\n<td>全国前10000</td>\n<td>2156</td>\n<td>2162</td>\n<td>2163</td>\n<td>2160</td>\n<td>2452</td>\n<td>218.6</td>\n</tr>\n<tr>\n<td>全国前1000</td>\n<td>2330</td>\n<td>2335</td>\n<td>2330</td>\n<td>2329</td>\n<td>2328</td>\n<td>2330.4</td>\n</tr>\n<tr>\n<td>全国前100</td>\n<td>2444</td>\n<td>2477</td>\n<td>2449</td>\n<td>2450</td>\n<td>2152</td>\n<td>2394.4</td>\n</tr>\n<tr>\n<td>巅峰第一</td>\n<td>2663</td>\n<td>2662</td>\n<td>2602</td>\n<td>2608</td>\n<td>2603</td>\n<td>2627.6</td>\n</tr>\n</tbody>\n</table>\n<h3 id=\"2-1-数据来源\">2.1 数据来源</h3>\n<h4 id=\"2-1-1-王者荣耀总玩家数量\">2.1.1 王者荣耀总玩家数量</h4>\n<p>根据王者荣耀2025年10月26日发布的B站专栏，王者荣耀日活用户突破1.39亿。因此本文使用这一数字作为王者荣耀玩家总数。</p>\n<h4 id=\"2-1-2-王者荣耀各分路排名及其对应的巅峰分数\">2.1.2 王者荣耀各分路排名及其对应的巅峰分数</h4>\n<p>作者于2026年3月29日12:30登陆王者荣耀安卓Q区，依次点击“排位”“巅峰赛”“奖励”“分路奖励”，整理当时各分路排名及对应的巅峰分数（见表1）。此时正处于S42赛季末，距离S43赛季更新仅剩2天，认为安卓Q区分数可代表王者荣耀全平台的巅峰赛分数，并且接下来两天的各分路巅峰分数不会有过大变化。</p>\n<h3 id=\"2-2-数学模型构建\">2.2 数学模型构建</h3>\n<h4 id=\"2-2-1-基本假设\">2.2.1 基本假设</h4>\n<p>根据大数定律与中心极限定理，玩家段位与巅峰赛分数分布应呈正态分布，即段位极低与巅峰分数极高的玩家占比均应极低，处于永恒钻石、至尊星耀这两个位于中间段位的玩家占比较高。</p>\n<h4 id=\"2-2-2-将最强王者以下段位转换为巅峰分\">2.2.2 将最强王者以下段位转换为巅峰分</h4>\n<p>为方便后续模拟，需要将最强王者以下的段位的“星数定段法”转换为巅峰赛相同的“分数定段法”。由作者本人实践得知，1200左右的巅峰赛赢一局加20分左右，暂不考虑高端局胜场巅峰分递减情况，认为最强王者段位及以下的难度均低于高分巅峰赛，因此胜场一颗星对应20分。</p>\n<p>众所周知，从倔强青铜III-1颗星到最强王者-1颗星，累计需升约100颗星，因此得到倔强青铜III-1颗星对应的巅峰分为：</p>\n<p><span class=\"katex-display\"><span class=\"katex\"><span class=\"katex-mathml\"><math xmlns=\"http://www.w3.org/1998/Math/MathML\" display=\"block\"><semantics><mrow><mn>1200</mn><mo>−</mo><mn>100</mn><mo>×</mo><mn>20</mn><mo>=</mo><mo>−</mo><mn>800</mn></mrow><annotation encoding=\"application/x-tex\">1200 - 100 \\times 20 = -800\n</annotation></semantics></math></span><span class=\"katex-html\" aria-hidden=\"true\"><span class=\"base\"><span class=\"strut\" style=\"height:0.7278em;vertical-align:-0.0833em;\"></span><span class=\"mord\">1200</span><span class=\"mspace\" style=\"margin-right:0.2222em;\"></span><span class=\"mbin\">−</span><span class=\"mspace\" style=\"margin-right:0.2222em;\"></span></span><span class=\"base\"><span class=\"strut\" style=\"height:0.7278em;vertical-align:-0.0833em;\"></span><span class=\"mord\">100</span><span class=\"mspace\" style=\"margin-right:0.2222em;\"></span><span class=\"mbin\">×</span><span class=\"mspace\" style=\"margin-right:0.2222em;\"></span></span><span class=\"base\"><span class=\"strut\" style=\"height:0.6444em;\"></span><span class=\"mord\">20</span><span class=\"mspace\" style=\"margin-right:0.2778em;\"></span><span class=\"mrel\">=</span><span class=\"mspace\" style=\"margin-right:0.2778em;\"></span></span><span class=\"base\"><span class=\"strut\" style=\"height:0.7278em;vertical-align:-0.0833em;\"></span><span class=\"mord\">−</span><span class=\"mord\">800</span></span></span></span></span></p>\n<p>这一段位的人数占比几乎为0。可佐证的是，如果在巅峰赛净胜场次100场，巅峰分数为3200分，在安卓Q区也没有人达到。根据目前巅峰第一最高分2627.6，向上取整并再向上取整至十位，为2630。因此我们能够得到，赛季末全段位巅峰分中位数为：</p>\n<p><span class=\"katex-display\"><span class=\"katex\"><span class=\"katex-mathml\"><math xmlns=\"http://www.w3.org/1998/Math/MathML\" display=\"block\"><semantics><mrow><mfrac><mrow><mo>−</mo><mn>800</mn><mo>+</mo><mn>2630</mn></mrow><mn>2</mn></mfrac><mo>=</mo><mn>915</mn></mrow><annotation encoding=\"application/x-tex\">\\frac{-800 + 2630}{2} = 915\n</annotation></semantics></math></span><span class=\"katex-html\" aria-hidden=\"true\"><span class=\"base\"><span class=\"strut\" style=\"height:2.0074em;vertical-align:-0.686em;\"></span><span class=\"mord\"><span class=\"mopen nulldelimiter\"></span><span class=\"mfrac\"><span class=\"vlist-t vlist-t2\"><span class=\"vlist-r\"><span class=\"vlist\" style=\"height:1.3214em;\"><span style=\"top:-2.314em;\"><span class=\"pstrut\" style=\"height:3em;\"></span><span class=\"mord\"><span class=\"mord\">2</span></span></span><span style=\"top:-3.23em;\"><span class=\"pstrut\" style=\"height:3em;\"></span><span class=\"frac-line\" style=\"border-bottom-width:0.04em;\"></span></span><span style=\"top:-3.677em;\"><span class=\"pstrut\" style=\"height:3em;\"></span><span class=\"mord\"><span class=\"mord\">−</span><span class=\"mord\">800</span><span class=\"mspace\" style=\"margin-right:0.2222em;\"></span><span class=\"mbin\">+</span><span class=\"mspace\" style=\"margin-right:0.2222em;\"></span><span class=\"mord\">2630</span></span></span></span><span class=\"vlist-s\">​</span></span><span class=\"vlist-r\"><span class=\"vlist\" style=\"height:0.686em;\"><span></span></span></span></span></span><span class=\"mclose nulldelimiter\"></span></span><span class=\"mspace\" style=\"margin-right:0.2778em;\"></span><span class=\"mrel\">=</span><span class=\"mspace\" style=\"margin-right:0.2778em;\"></span></span><span class=\"base\"><span class=\"strut\" style=\"height:0.6444em;\"></span><span class=\"mord\">915</span></span></span></span></span></p>\n<p>即赛季末期，至尊星耀III-1颗星的玩家占比最高，符合2.2.1的基本假设。并且，915就是接下来构建的正态分布模型的 μ值。</p>\n<h4 id=\"2-2-3-数学模型计算方法\">2.2.3 数学模型计算方法</h4>\n<p>正态分布基本公式为：</p>\n<p><span class=\"katex-display\"><span class=\"katex\"><span class=\"katex-mathml\"><math xmlns=\"http://www.w3.org/1998/Math/MathML\" display=\"block\"><semantics><mrow><mi>f</mi><mo stretchy=\"false\">(</mo><mi>x</mi><mo stretchy=\"false\">)</mo><mo>=</mo><mfrac><mn>1</mn><mrow><msqrt><mrow><mn>2</mn><mi>π</mi></mrow></msqrt><mtext> </mtext><mi>σ</mi></mrow></mfrac><msup><mi>e</mi><mrow><mo>−</mo><mfrac><mrow><mo stretchy=\"false\">(</mo><mi>x</mi><mo>−</mo><mi>μ</mi><msup><mo stretchy=\"false\">)</mo><mn>2</mn></msup></mrow><mrow><mn>2</mn><msup><mi>σ</mi><mn>2</mn></msup></mrow></mfrac></mrow></msup></mrow><annotation encoding=\"application/x-tex\">f(x) = \\frac{1}{\\sqrt{2\\pi}\\,\\sigma} e^{-\\frac{(x - \\mu)^2}{2\\sigma^2}}\n</annotation></semantics></math></span><span class=\"katex-html\" aria-hidden=\"true\"><span class=\"base\"><span class=\"strut\" style=\"height:1em;vertical-align:-0.25em;\"></span><span class=\"mord mathnormal\" style=\"margin-right:0.10764em;\">f</span><span class=\"mopen\">(</span><span class=\"mord mathnormal\">x</span><span class=\"mclose\">)</span><span class=\"mspace\" style=\"margin-right:0.2778em;\"></span><span class=\"mrel\">=</span><span class=\"mspace\" style=\"margin-right:0.2778em;\"></span></span><span class=\"base\"><span class=\"strut\" style=\"height:2.2591em;vertical-align:-0.93em;\"></span><span class=\"mord\"><span class=\"mopen nulldelimiter\"></span><span class=\"mfrac\"><span class=\"vlist-t vlist-t2\"><span class=\"vlist-r\"><span class=\"vlist\" style=\"height:1.3214em;\"><span style=\"top:-2.2028em;\"><span class=\"pstrut\" style=\"height:3em;\"></span><span class=\"mord\"><span class=\"mord sqrt\"><span class=\"vlist-t vlist-t2\"><span class=\"vlist-r\"><span class=\"vlist\" style=\"height:0.9072em;\"><span class=\"svg-align\" style=\"top:-3em;\"><span class=\"pstrut\" style=\"height:3em;\"></span><span class=\"mord\" style=\"padding-left:0.833em;\"><span class=\"mord\">2</span><span class=\"mord mathnormal\" style=\"margin-right:0.03588em;\">π</span></span></span><span style=\"top:-2.8672em;\"><span class=\"pstrut\" style=\"height:3em;\"></span><span class=\"hide-tail\" style=\"min-width:0.853em;height:1.08em;\"><svg xmlns=\"http://www.w3.org/2000/svg\" width=\"400em\" height=\"1.08em\" viewBox=\"0 0 400000 1080\" preserveAspectRatio=\"xMinYMin slice\"><path d=\"M95,702\nc-2.7,0,-7.17,-2.7,-13.5,-8c-5.8,-5.3,-9.5,-10,-9.5,-14\nc0,-2,0.3,-3.3,1,-4c1.3,-2.7,23.83,-20.7,67.5,-54\nc44.2,-33.3,65.8,-50.3,66.5,-51c1.3,-1.3,3,-2,5,-2c4.7,0,8.7,3.3,12,10\ns173,378,173,378c0.7,0,35.3,-71,104,-213c68.7,-142,137.5,-285,206.5,-429\nc69,-144,104.5,-217.7,106.5,-221\nl0 -0\nc5.3,-9.3,12,-14,20,-14\nH400000v40H845.2724\ns-225.272,467,-225.272,467s-235,486,-235,486c-2.7,4.7,-9,7,-19,7\nc-6,0,-10,-1,-12,-3s-194,-422,-194,-422s-65,47,-65,47z\nM834 80h400000v40h-400000z\"/></svg></span></span></span><span class=\"vlist-s\">​</span></span><span class=\"vlist-r\"><span class=\"vlist\" style=\"height:0.1328em;\"><span></span></span></span></span></span><span class=\"mspace\" style=\"margin-right:0.1667em;\"></span><span class=\"mord mathnormal\" style=\"margin-right:0.03588em;\">σ</span></span></span><span style=\"top:-3.23em;\"><span class=\"pstrut\" style=\"height:3em;\"></span><span class=\"frac-line\" style=\"border-bottom-width:0.04em;\"></span></span><span style=\"top:-3.677em;\"><span class=\"pstrut\" style=\"height:3em;\"></span><span class=\"mord\"><span class=\"mord\">1</span></span></span></span><span class=\"vlist-s\">​</span></span><span class=\"vlist-r\"><span class=\"vlist\" style=\"height:0.93em;\"><span></span></span></span></span></span><span class=\"mclose nulldelimiter\"></span></span><span class=\"mord\"><span class=\"mord mathnormal\">e</span><span class=\"msupsub\"><span class=\"vlist-t\"><span class=\"vlist-r\"><span class=\"vlist\" style=\"height:1.3291em;\"><span style=\"top:-3.4534em;margin-right:0.05em;\"><span class=\"pstrut\" style=\"height:3em;\"></span><span class=\"sizing reset-size6 size3 mtight\"><span class=\"mord mtight\"><span class=\"mord mtight\">−</span><span class=\"mord mtight\"><span class=\"mopen nulldelimiter sizing reset-size3 size6\"></span><span class=\"mfrac\"><span class=\"vlist-t vlist-t2\"><span class=\"vlist-r\"><span class=\"vlist\" style=\"height:1.251em;\"><span style=\"top:-2.5062em;\"><span class=\"pstrut\" style=\"height:3em;\"></span><span class=\"sizing reset-size3 size1 mtight\"><span class=\"mord mtight\"><span class=\"mord mtight\">2</span><span class=\"mord mtight\"><span class=\"mord mathnormal mtight\" style=\"margin-right:0.03588em;\">σ</span><span class=\"msupsub\"><span class=\"vlist-t\"><span class=\"vlist-r\"><span class=\"vlist\" style=\"height:0.9384em;\"><span style=\"top:-2.9384em;margin-right:0.1em;\"><span class=\"pstrut\" style=\"height:2.6444em;\"></span><span class=\"mord mtight\">2</span></span></span></span></span></span></span></span></span></span><span style=\"top:-3.2255em;\"><span class=\"pstrut\" style=\"height:3em;\"></span><span class=\"frac-line mtight\" style=\"border-bottom-width:0.049em;\"></span></span><span style=\"top:-3.5021em;\"><span class=\"pstrut\" style=\"height:3em;\"></span><span class=\"sizing reset-size3 size1 mtight\"><span class=\"mord mtight\"><span class=\"mopen mtight\">(</span><span class=\"mord mathnormal mtight\">x</span><span class=\"mbin mtight\">−</span><span class=\"mord mathnormal mtight\">μ</span><span class=\"mclose mtight\"><span class=\"mclose mtight\">)</span><span class=\"msupsub\"><span class=\"vlist-t\"><span class=\"vlist-r\"><span class=\"vlist\" style=\"height:1.0484em;\"><span style=\"top:-3.0484em;margin-right:0.1em;\"><span class=\"pstrut\" style=\"height:2.6444em;\"></span><span class=\"mord mtight\">2</span></span></span></span></span></span></span></span></span></span></span><span class=\"vlist-s\">​</span></span><span class=\"vlist-r\"><span class=\"vlist\" style=\"height:0.4938em;\"><span></span></span></span></span></span><span class=\"mclose nulldelimiter sizing reset-size3 size6\"></span></span></span></span></span></span></span></span></span></span></span></span></span></span></p>\n<p>其分布函数为：</p>\n<p><span class=\"katex-display\"><span class=\"katex\"><span class=\"katex-mathml\"><math xmlns=\"http://www.w3.org/1998/Math/MathML\" display=\"block\"><semantics><mrow><mi>F</mi><mo stretchy=\"false\">(</mo><mi>x</mi><mo stretchy=\"false\">)</mo><mo>=</mo><msubsup><mo>∫</mo><mrow><mo>−</mo><mi mathvariant=\"normal\">∞</mi></mrow><mi>x</mi></msubsup><mfrac><mn>1</mn><mrow><msqrt><mrow><mn>2</mn><mi>π</mi></mrow></msqrt><mtext> </mtext><mi>σ</mi></mrow></mfrac><msup><mi>e</mi><mrow><mo>−</mo><mfrac><mrow><mo stretchy=\"false\">(</mo><mi>t</mi><mo>−</mo><mi>μ</mi><msup><mo stretchy=\"false\">)</mo><mn>2</mn></msup></mrow><mrow><mn>2</mn><msup><mi>σ</mi><mn>2</mn></msup></mrow></mfrac></mrow></msup><mtext> </mtext><mi>d</mi><mi>t</mi></mrow><annotation encoding=\"application/x-tex\">F(x) = \\int_{-\\infty}^{x} \\frac{1}{\\sqrt{2\\pi}\\,\\sigma} e^{-\\frac{(t - \\mu)^2}{2\\sigma^2}} \\, dt\n</annotation></semantics></math></span><span class=\"katex-html\" aria-hidden=\"true\"><span class=\"base\"><span class=\"strut\" style=\"height:1em;vertical-align:-0.25em;\"></span><span class=\"mord mathnormal\" style=\"margin-right:0.13889em;\">F</span><span class=\"mopen\">(</span><span class=\"mord mathnormal\">x</span><span class=\"mclose\">)</span><span class=\"mspace\" style=\"margin-right:0.2778em;\"></span><span class=\"mrel\">=</span><span class=\"mspace\" style=\"margin-right:0.2778em;\"></span></span><span class=\"base\"><span class=\"strut\" style=\"height:2.3846em;vertical-align:-0.9703em;\"></span><span class=\"mop\"><span class=\"mop op-symbol large-op\" style=\"margin-right:0.44445em;position:relative;top:-0.0011em;\">∫</span><span class=\"msupsub\"><span class=\"vlist-t vlist-t2\"><span class=\"vlist-r\"><span class=\"vlist\" style=\"height:1.4143em;\"><span style=\"top:-1.7881em;margin-left:-0.4445em;margin-right:0.05em;\"><span class=\"pstrut\" style=\"height:2.7em;\"></span><span class=\"sizing reset-size6 size3 mtight\"><span class=\"mord mtight\"><span class=\"mord mtight\">−</span><span class=\"mord mtight\">∞</span></span></span></span><span style=\"top:-3.8129em;margin-right:0.05em;\"><span class=\"pstrut\" style=\"height:2.7em;\"></span><span class=\"sizing reset-size6 size3 mtight\"><span class=\"mord mtight\"><span class=\"mord mathnormal mtight\">x</span></span></span></span></span><span class=\"vlist-s\">​</span></span><span class=\"vlist-r\"><span class=\"vlist\" style=\"height:0.9703em;\"><span></span></span></span></span></span></span><span class=\"mspace\" style=\"margin-right:0.1667em;\"></span><span class=\"mord\"><span class=\"mopen nulldelimiter\"></span><span class=\"mfrac\"><span class=\"vlist-t vlist-t2\"><span class=\"vlist-r\"><span class=\"vlist\" style=\"height:1.3214em;\"><span style=\"top:-2.2028em;\"><span class=\"pstrut\" style=\"height:3em;\"></span><span class=\"mord\"><span class=\"mord sqrt\"><span class=\"vlist-t vlist-t2\"><span class=\"vlist-r\"><span class=\"vlist\" style=\"height:0.9072em;\"><span class=\"svg-align\" style=\"top:-3em;\"><span class=\"pstrut\" style=\"height:3em;\"></span><span class=\"mord\" style=\"padding-left:0.833em;\"><span class=\"mord\">2</span><span class=\"mord mathnormal\" style=\"margin-right:0.03588em;\">π</span></span></span><span style=\"top:-2.8672em;\"><span class=\"pstrut\" style=\"height:3em;\"></span><span class=\"hide-tail\" style=\"min-width:0.853em;height:1.08em;\"><svg xmlns=\"http://www.w3.org/2000/svg\" width=\"400em\" height=\"1.08em\" viewBox=\"0 0 400000 1080\" preserveAspectRatio=\"xMinYMin slice\"><path d=\"M95,702\nc-2.7,0,-7.17,-2.7,-13.5,-8c-5.8,-5.3,-9.5,-10,-9.5,-14\nc0,-2,0.3,-3.3,1,-4c1.3,-2.7,23.83,-20.7,67.5,-54\nc44.2,-33.3,65.8,-50.3,66.5,-51c1.3,-1.3,3,-2,5,-2c4.7,0,8.7,3.3,12,10\ns173,378,173,378c0.7,0,35.3,-71,104,-213c68.7,-142,137.5,-285,206.5,-429\nc69,-144,104.5,-217.7,106.5,-221\nl0 -0\nc5.3,-9.3,12,-14,20,-14\nH400000v40H845.2724\ns-225.272,467,-225.272,467s-235,486,-235,486c-2.7,4.7,-9,7,-19,7\nc-6,0,-10,-1,-12,-3s-194,-422,-194,-422s-65,47,-65,47z\nM834 80h400000v40h-400000z\"/></svg></span></span></span><span class=\"vlist-s\">​</span></span><span class=\"vlist-r\"><span class=\"vlist\" style=\"height:0.1328em;\"><span></span></span></span></span></span><span class=\"mspace\" style=\"margin-right:0.1667em;\"></span><span class=\"mord mathnormal\" style=\"margin-right:0.03588em;\">σ</span></span></span><span style=\"top:-3.23em;\"><span class=\"pstrut\" style=\"height:3em;\"></span><span class=\"frac-line\" style=\"border-bottom-width:0.04em;\"></span></span><span style=\"top:-3.677em;\"><span class=\"pstrut\" style=\"height:3em;\"></span><span class=\"mord\"><span class=\"mord\">1</span></span></span></span><span class=\"vlist-s\">​</span></span><span class=\"vlist-r\"><span class=\"vlist\" style=\"height:0.93em;\"><span></span></span></span></span></span><span class=\"mclose nulldelimiter\"></span></span><span class=\"mord\"><span class=\"mord mathnormal\">e</span><span class=\"msupsub\"><span class=\"vlist-t\"><span class=\"vlist-r\"><span class=\"vlist\" style=\"height:1.3291em;\"><span style=\"top:-3.4534em;margin-right:0.05em;\"><span class=\"pstrut\" style=\"height:3em;\"></span><span class=\"sizing reset-size6 size3 mtight\"><span class=\"mord mtight\"><span class=\"mord mtight\">−</span><span class=\"mord mtight\"><span class=\"mopen nulldelimiter sizing reset-size3 size6\"></span><span class=\"mfrac\"><span class=\"vlist-t vlist-t2\"><span class=\"vlist-r\"><span class=\"vlist\" style=\"height:1.251em;\"><span style=\"top:-2.5062em;\"><span class=\"pstrut\" style=\"height:3em;\"></span><span class=\"sizing reset-size3 size1 mtight\"><span class=\"mord mtight\"><span class=\"mord mtight\">2</span><span class=\"mord mtight\"><span class=\"mord mathnormal mtight\" style=\"margin-right:0.03588em;\">σ</span><span class=\"msupsub\"><span class=\"vlist-t\"><span class=\"vlist-r\"><span class=\"vlist\" style=\"height:0.9384em;\"><span style=\"top:-2.9384em;margin-right:0.1em;\"><span class=\"pstrut\" style=\"height:2.6444em;\"></span><span class=\"mord mtight\">2</span></span></span></span></span></span></span></span></span></span><span style=\"top:-3.2255em;\"><span class=\"pstrut\" style=\"height:3em;\"></span><span class=\"frac-line mtight\" style=\"border-bottom-width:0.049em;\"></span></span><span style=\"top:-3.5021em;\"><span class=\"pstrut\" style=\"height:3em;\"></span><span class=\"sizing reset-size3 size1 mtight\"><span class=\"mord mtight\"><span class=\"mopen mtight\">(</span><span class=\"mord mathnormal mtight\">t</span><span class=\"mbin mtight\">−</span><span class=\"mord mathnormal mtight\">μ</span><span class=\"mclose mtight\"><span class=\"mclose mtight\">)</span><span class=\"msupsub\"><span class=\"vlist-t\"><span class=\"vlist-r\"><span class=\"vlist\" style=\"height:1.0484em;\"><span style=\"top:-3.0484em;margin-right:0.1em;\"><span class=\"pstrut\" style=\"height:2.6444em;\"></span><span class=\"mord mtight\">2</span></span></span></span></span></span></span></span></span></span></span><span class=\"vlist-s\">​</span></span><span class=\"vlist-r\"><span class=\"vlist\" style=\"height:0.4938em;\"><span></span></span></span></span></span><span class=\"mclose nulldelimiter sizing reset-size3 size6\"></span></span></span></span></span></span></span></span></span></span><span class=\"mspace\" style=\"margin-right:0.1667em;\"></span><span class=\"mord mathnormal\">d</span><span class=\"mord mathnormal\">t</span></span></span></span></span></p>\n<p>分别使用全国万强、全国千强、全国百强的平均巅峰分数代入x，结合μ值以及玩家占比，求解得到 σ。值得注意的是，因为每条分路均有足量的玩家，分布玩家总数量分别为50000、5000、500，而不是10000、1000、100与玩家总人数做比。</p>\n<h4 id=\"2-2-4-数学模型验证\">2.2.4 数学模型验证</h4>\n<p>共得到3个模型，每个模型使用未参与构建的另外三个巅峰分与占比进行检验。即将另外三个分路排名的平均巅峰分代入后，得到这三个分路排名玩家的占比，与真实占比进行比较，选取预测和实际值最接近的模型作为本研究最终结果。</p>\n<h3 id=\"2-3-计算高端局对应的巅峰分数\">2.3 计算高端局对应的巅峰分数</h3>\n<p>本质上，与高端局对应的是普通对局，普通对局又可以理解为常见对局。根据统计学原理，(95%) 的玩家所处的对局为“正常对局”，高端局可以被看成低概率出现的“异常对局”。因此使用最优的分布模型，依次代入 (F(x) = 0.95)、(0.975)、(0.99)、(0.999)，解出的 (x) 值（四舍五入处理）就是对应该玩家已经超越了全王者人员 (95%)、(97.5%)、(99%)、(99.9%) 的玩家，其所处的对局就是王者荣耀数学意义上的高端局，即前 (5%)、(2.5%)、(1%)、(0.1%) 的对局。</p>\n<p>使用Python进行本研究全部复杂计算与绘图。</p>\n<h3 id=\"2-4-赛季不同时段高端局判断方法\">2.4 赛季不同时段高端局判断方法</h3>\n<p>众所周知，随着玩家的胜败，赛季初与赛季末的巅峰赛分数不同，因此对应的高端局判定标准也必然不一致。在这里，作者结合上述研究成果，开发出一个Python算法，玩家可以通过输入实时的巅峰第一分数与巅峰万强分数，计算此时王者荣耀高端局对应的占比。</p>\n<h2 id=\"3-结果与讨论\">3 结果与讨论</h2>\n<h3 id=\"3-1-各数学模型计算与检验结果\">3.1 各数学模型计算与检验结果</h3>\n<p>图1表明，使用巅峰万强为输入数据的模型效果最好。</p>\n<p><img src=\"https://img.rubbish.press/file/2604/1775660622597_image.png\" alt=\"\"></p>\n<center>图1 三个模型构建后，使用未参与构建的指标进行检验的预测值与实际值对比，其中a、b、c图分别为使用巅峰万强、巅峰千强、巅峰百强数据构建</center>\n<h3 id=\"3-2-高端局对应巅峰分\">3.2 高端局对应巅峰分</h3>\n<p>经计算，前 (5%)、(2.5%)、(1%)、(0.1%) 的对局对应的巅峰分依次为1549、1671、1812、2106（图2）。因此，只要玩家的巅峰赛分数达到1549分及以上，就可以认为该玩家已经跨入“高端局”的门槛；如果该玩家巅峰分数达到1812分及以上，那么这位玩家的实力已经超越全王者人员 (99%) 的玩家；如果一位玩家的巅峰分数达到2106分及以上，那么可以认为，1000名王者荣耀玩家中，才会有1名这样的玩家。</p>\n<p><img src=\"https://img.rubbish.press/file/2604/1775660644485_image.png\" alt=\"\"></p>\n<center>图2 赛季末巅峰分数与低于对应巅峰分玩家占比的关系，图像上的点表示前 5%、2.5%、1%、0.1%的对局对应的巅峰分</center>\n<h3 id=\"3-3-不同时段的高端局衡量方法\">3.3 不同时段的高端局衡量方法</h3>\n<p>本研究使用的所有代码，以及开发用于实时确定高端局的Python算法可以在 <a href=\"https://gitee.com/wys477474310/avz/tree/master/\">https://gitee.com/wys477474310/avz/tree/master/</a> 获取。</p>\n<h2 id=\"4-结论\">4 结论</h2>\n<p>本研究指出，前 (5%)、(2.5%)、(1%)、(0.1%) 的对局对应的巅峰分依次为1549、1671、1812、2106。因此，只要达到以上这些分数，你就拥有了在网络上炫耀的资本。如果有人质疑，你就将这篇论文糊在他的脸上，让他去发表反驳我的论文。</p>\n<h2 id=\"声明\">声明</h2>\n<p>由于作者不是计算机专业，因此没有实力将该算法包装为小软件或小程序。不过如果有高技术人才能做到这一点，希望你在软件或程序中，加入本人或本论文的引用信息。如果希望指出错误或能改进的地方，请看作者下面的那个邮箱，可以联系到我，但我基本不登录QQ，所以能否回复、是否有时间改进，都是问题。</p>\n<h2 id=\"致谢\">致谢</h2>\n<p>感谢我的两位室友带我入坑王者荣耀，没有说我室友不好的意思，但是可能我上辈子作恶多端，这辈子玩到了王者荣耀这个游戏。</p>\n<h2 id=\"参考文献\">参考文献</h2>\n<p>[1] 陈海遥王者教学. 【王者数据科普】什么是高分段，梯度要怎么看？. bilibili. <a href=\"https://www.bilibili.com/video/BV1VHkwBNE6p\">https://www.bilibili.com/video/BV1VHkwBNE6p</a>.</p>\n<p>[2] 韩云青不涨粉. 聊一下多少分算高手. bilibili. <a href=\"https://www.bilibili.com/video/BV17JsmzGEgo\">https://www.bilibili.com/video/BV17JsmzGEgo</a>.</p>\n<p>[3] 困境王者导师. 王者荣耀实力层级划分，一期视频让你真正了解各个分段的含金量（各个分段的突破方法）. bilibili. <a href=\"https://www.bilibili.com/video/BV1KDWFzQENc\">https://www.bilibili.com/video/BV1KDWFzQENc</a>.</p>\n<p>[4] 王者荣耀. #王者荣耀2025年国服日活用户数突破1.39亿#. bilibili. <a href=\"https://www.bilibili.com/opus/1128016960652574742\">https://www.bilibili.com/opus/1128016960652574742</a></p>\n","more":"<p>橙子.dyib(^{1*})，SLz(^{1*})，Marry a Sunset(^{1*})，Experiment in Prison(^{1*})，Big Full Stick(^{2})</p>\n<p>1 bgu.45j.632<br>\n2 bgu.45j.629<br>\n(*)3287932348@qq.com<br>\n同等贡献</p>\n<!-- 以下请在href=后的双引号里填写pdf全网链接 -->\n<a href=\"https://file.rubbish.press/artical/%E4%B8%80%E4%B8%AA%E8%80%83%E5%AF%9F%E7%8E%8B%E8%80%85%E8%8D%A3%E8%80%80%E7%8E%A9%E5%AE%B6%E6%98%AF%E5%90%A6%E5%A4%84%E4%BA%8E%E9%AB%98%E7%AB%AF%E5%B1%80%E7%9A%84%E6%95%B0%E5%AD%A6%E6%A8%A1%E5%9E%8B%E4%B8%8E%E7%AE%97%E6%B3%95.pdf?preview\" target=\"_blank\" style=\"display: inline-flex; align-items: center; gap: 8px; padding: 10px 18px; background: #2563eb; color: white; border-radius: 8px; text-decoration: none; font-size: 15px; font-weight: 500; transition: all 0.2s;\">\n  <svg style=\"width:18px;height:18px;fill:currentColor;\" viewBox=\"0 0 24 24\">\n    <path d=\"M20 2H8c-1.1 0-2 .9-2 2v12c0 1.1.9 2 2 2h12c1.1 0 2-.9 2-2V4c0-1.1-.9-2-2-2zm0 14H8V4h12v12zM4 6H2v14c0 1.1.9 2 2 2h14v-2H4V6zm12 6V9l-4 4-4-4v3h8z\"/>\n  </svg>\n  阅读 PDF 全文\n</a>\n<h2 id=\"摘要\">摘要</h2>\n<p>王者荣耀高端局的判定标准一直是玩家们津津乐道的一个话题，但是从未有人使用严谨的数学方法给出准确的判断标准。本文通过王者荣耀真实数据与正态分布模型相结合的方法，提出“星数定段法”向“分数定段法”的计算方法，构建了王者荣耀巅峰赛分数与能够达到该分数的玩家的比例关系。结果显示，当玩家的赛季末巅峰赛分数达到1549、1670、1812、2106分时，说明该玩家已经超过了王者荣耀 (95%)、(97.5%)、(99%)、(99.9%) 的玩家。并且，本研究还给出了一个能够通过实时巅峰万强与巅峰第一的分数，实时计算王者荣耀高端局对应的巅峰赛分数的Python算法。</p>\n<p><strong>关键词：</strong> 王者荣耀；高端局；数学模型；正态分布</p>\n<h2 id=\"1-引言\">1 引言</h2>\n<p>作为一款现象级国民游戏，王者荣耀各个方面均有大量玩家讨论，尤其是“英雄强度”这一问题。双方玩家通常会拿出自己的巅峰分数或者英雄战力，来表明自己对王者荣耀的理解程度，而另一方回击的方法，就是说“这根本不算高端局”等等。网上关于什么算是有含金量的高端局的讨论也层出不穷[1,2,3]。造成这一现象的重要原因，就是没有一个准确的算法指出，哪类对局算是所谓的“高端局”。因此，一个准确的用来衡量王者荣耀对局水平的数学模型迫在眉睫。</p>\n<h2 id=\"2-研究方法\">2 研究方法</h2>\n<p>本文希望构建一个模型并给出普适性算法，根据玩家王者荣耀巅峰分数以及该时段王者荣耀各分路巅峰万强等分数，来确定该玩家的对局处于什么水平。</p>\n<p><strong>表1</strong> 2026年3月29日12:30王者荣耀安卓Q区各分路排名及其对应的巅峰分数，将这些分数进行算术平均处理，得到最后一列“平均”的值</p>\n<table>\n<thead>\n<tr>\n<th>分路排名</th>\n<th>对抗路</th>\n<th>打野</th>\n<th>中路</th>\n<th>发育路</th>\n<th>游走</th>\n<th>平均</th>\n</tr>\n</thead>\n<tbody>\n<tr>\n<td>全国前10000</td>\n<td>2156</td>\n<td>2162</td>\n<td>2163</td>\n<td>2160</td>\n<td>2452</td>\n<td>218.6</td>\n</tr>\n<tr>\n<td>全国前1000</td>\n<td>2330</td>\n<td>2335</td>\n<td>2330</td>\n<td>2329</td>\n<td>2328</td>\n<td>2330.4</td>\n</tr>\n<tr>\n<td>全国前100</td>\n<td>2444</td>\n<td>2477</td>\n<td>2449</td>\n<td>2450</td>\n<td>2152</td>\n<td>2394.4</td>\n</tr>\n<tr>\n<td>巅峰第一</td>\n<td>2663</td>\n<td>2662</td>\n<td>2602</td>\n<td>2608</td>\n<td>2603</td>\n<td>2627.6</td>\n</tr>\n</tbody>\n</table>\n<h3 id=\"2-1-数据来源\">2.1 数据来源</h3>\n<h4 id=\"2-1-1-王者荣耀总玩家数量\">2.1.1 王者荣耀总玩家数量</h4>\n<p>根据王者荣耀2025年10月26日发布的B站专栏，王者荣耀日活用户突破1.39亿。因此本文使用这一数字作为王者荣耀玩家总数。</p>\n<h4 id=\"2-1-2-王者荣耀各分路排名及其对应的巅峰分数\">2.1.2 王者荣耀各分路排名及其对应的巅峰分数</h4>\n<p>作者于2026年3月29日12:30登陆王者荣耀安卓Q区，依次点击“排位”“巅峰赛”“奖励”“分路奖励”，整理当时各分路排名及对应的巅峰分数（见表1）。此时正处于S42赛季末，距离S43赛季更新仅剩2天，认为安卓Q区分数可代表王者荣耀全平台的巅峰赛分数，并且接下来两天的各分路巅峰分数不会有过大变化。</p>\n<h3 id=\"2-2-数学模型构建\">2.2 数学模型构建</h3>\n<h4 id=\"2-2-1-基本假设\">2.2.1 基本假设</h4>\n<p>根据大数定律与中心极限定理，玩家段位与巅峰赛分数分布应呈正态分布，即段位极低与巅峰分数极高的玩家占比均应极低，处于永恒钻石、至尊星耀这两个位于中间段位的玩家占比较高。</p>\n<h4 id=\"2-2-2-将最强王者以下段位转换为巅峰分\">2.2.2 将最强王者以下段位转换为巅峰分</h4>\n<p>为方便后续模拟，需要将最强王者以下的段位的“星数定段法”转换为巅峰赛相同的“分数定段法”。由作者本人实践得知，1200左右的巅峰赛赢一局加20分左右，暂不考虑高端局胜场巅峰分递减情况，认为最强王者段位及以下的难度均低于高分巅峰赛，因此胜场一颗星对应20分。</p>\n<p>众所周知，从倔强青铜III-1颗星到最强王者-1颗星，累计需升约100颗星，因此得到倔强青铜III-1颗星对应的巅峰分为：</p>\n<p><span class=\"katex-display\"><span class=\"katex\"><span class=\"katex-mathml\"><math xmlns=\"http://www.w3.org/1998/Math/MathML\" display=\"block\"><semantics><mrow><mn>1200</mn><mo>−</mo><mn>100</mn><mo>×</mo><mn>20</mn><mo>=</mo><mo>−</mo><mn>800</mn></mrow><annotation encoding=\"application/x-tex\">1200 - 100 \\times 20 = -800\n</annotation></semantics></math></span><span class=\"katex-html\" aria-hidden=\"true\"><span class=\"base\"><span class=\"strut\" style=\"height:0.7278em;vertical-align:-0.0833em;\"></span><span class=\"mord\">1200</span><span class=\"mspace\" style=\"margin-right:0.2222em;\"></span><span class=\"mbin\">−</span><span class=\"mspace\" style=\"margin-right:0.2222em;\"></span></span><span class=\"base\"><span class=\"strut\" style=\"height:0.7278em;vertical-align:-0.0833em;\"></span><span class=\"mord\">100</span><span class=\"mspace\" style=\"margin-right:0.2222em;\"></span><span class=\"mbin\">×</span><span class=\"mspace\" style=\"margin-right:0.2222em;\"></span></span><span class=\"base\"><span class=\"strut\" style=\"height:0.6444em;\"></span><span class=\"mord\">20</span><span class=\"mspace\" style=\"margin-right:0.2778em;\"></span><span class=\"mrel\">=</span><span class=\"mspace\" style=\"margin-right:0.2778em;\"></span></span><span class=\"base\"><span class=\"strut\" style=\"height:0.7278em;vertical-align:-0.0833em;\"></span><span class=\"mord\">−</span><span class=\"mord\">800</span></span></span></span></span></p>\n<p>这一段位的人数占比几乎为0。可佐证的是，如果在巅峰赛净胜场次100场，巅峰分数为3200分，在安卓Q区也没有人达到。根据目前巅峰第一最高分2627.6，向上取整并再向上取整至十位，为2630。因此我们能够得到，赛季末全段位巅峰分中位数为：</p>\n<p><span class=\"katex-display\"><span class=\"katex\"><span class=\"katex-mathml\"><math xmlns=\"http://www.w3.org/1998/Math/MathML\" display=\"block\"><semantics><mrow><mfrac><mrow><mo>−</mo><mn>800</mn><mo>+</mo><mn>2630</mn></mrow><mn>2</mn></mfrac><mo>=</mo><mn>915</mn></mrow><annotation encoding=\"application/x-tex\">\\frac{-800 + 2630}{2} = 915\n</annotation></semantics></math></span><span class=\"katex-html\" aria-hidden=\"true\"><span class=\"base\"><span class=\"strut\" style=\"height:2.0074em;vertical-align:-0.686em;\"></span><span class=\"mord\"><span class=\"mopen nulldelimiter\"></span><span class=\"mfrac\"><span class=\"vlist-t vlist-t2\"><span class=\"vlist-r\"><span class=\"vlist\" style=\"height:1.3214em;\"><span style=\"top:-2.314em;\"><span class=\"pstrut\" style=\"height:3em;\"></span><span class=\"mord\"><span class=\"mord\">2</span></span></span><span style=\"top:-3.23em;\"><span class=\"pstrut\" style=\"height:3em;\"></span><span class=\"frac-line\" style=\"border-bottom-width:0.04em;\"></span></span><span style=\"top:-3.677em;\"><span class=\"pstrut\" style=\"height:3em;\"></span><span class=\"mord\"><span class=\"mord\">−</span><span class=\"mord\">800</span><span class=\"mspace\" style=\"margin-right:0.2222em;\"></span><span class=\"mbin\">+</span><span class=\"mspace\" style=\"margin-right:0.2222em;\"></span><span class=\"mord\">2630</span></span></span></span><span class=\"vlist-s\">​</span></span><span class=\"vlist-r\"><span class=\"vlist\" style=\"height:0.686em;\"><span></span></span></span></span></span><span class=\"mclose nulldelimiter\"></span></span><span class=\"mspace\" style=\"margin-right:0.2778em;\"></span><span class=\"mrel\">=</span><span class=\"mspace\" style=\"margin-right:0.2778em;\"></span></span><span class=\"base\"><span class=\"strut\" style=\"height:0.6444em;\"></span><span class=\"mord\">915</span></span></span></span></span></p>\n<p>即赛季末期，至尊星耀III-1颗星的玩家占比最高，符合2.2.1的基本假设。并且，915就是接下来构建的正态分布模型的 μ值。</p>\n<h4 id=\"2-2-3-数学模型计算方法\">2.2.3 数学模型计算方法</h4>\n<p>正态分布基本公式为：</p>\n<p><span class=\"katex-display\"><span class=\"katex\"><span class=\"katex-mathml\"><math xmlns=\"http://www.w3.org/1998/Math/MathML\" display=\"block\"><semantics><mrow><mi>f</mi><mo stretchy=\"false\">(</mo><mi>x</mi><mo stretchy=\"false\">)</mo><mo>=</mo><mfrac><mn>1</mn><mrow><msqrt><mrow><mn>2</mn><mi>π</mi></mrow></msqrt><mtext> </mtext><mi>σ</mi></mrow></mfrac><msup><mi>e</mi><mrow><mo>−</mo><mfrac><mrow><mo stretchy=\"false\">(</mo><mi>x</mi><mo>−</mo><mi>μ</mi><msup><mo stretchy=\"false\">)</mo><mn>2</mn></msup></mrow><mrow><mn>2</mn><msup><mi>σ</mi><mn>2</mn></msup></mrow></mfrac></mrow></msup></mrow><annotation encoding=\"application/x-tex\">f(x) = \\frac{1}{\\sqrt{2\\pi}\\,\\sigma} e^{-\\frac{(x - \\mu)^2}{2\\sigma^2}}\n</annotation></semantics></math></span><span class=\"katex-html\" aria-hidden=\"true\"><span class=\"base\"><span class=\"strut\" style=\"height:1em;vertical-align:-0.25em;\"></span><span class=\"mord mathnormal\" style=\"margin-right:0.10764em;\">f</span><span class=\"mopen\">(</span><span class=\"mord mathnormal\">x</span><span class=\"mclose\">)</span><span class=\"mspace\" style=\"margin-right:0.2778em;\"></span><span class=\"mrel\">=</span><span class=\"mspace\" style=\"margin-right:0.2778em;\"></span></span><span class=\"base\"><span class=\"strut\" style=\"height:2.2591em;vertical-align:-0.93em;\"></span><span class=\"mord\"><span class=\"mopen nulldelimiter\"></span><span class=\"mfrac\"><span class=\"vlist-t vlist-t2\"><span class=\"vlist-r\"><span class=\"vlist\" style=\"height:1.3214em;\"><span style=\"top:-2.2028em;\"><span class=\"pstrut\" style=\"height:3em;\"></span><span class=\"mord\"><span class=\"mord sqrt\"><span class=\"vlist-t vlist-t2\"><span class=\"vlist-r\"><span class=\"vlist\" style=\"height:0.9072em;\"><span class=\"svg-align\" style=\"top:-3em;\"><span class=\"pstrut\" style=\"height:3em;\"></span><span class=\"mord\" style=\"padding-left:0.833em;\"><span class=\"mord\">2</span><span class=\"mord mathnormal\" style=\"margin-right:0.03588em;\">π</span></span></span><span style=\"top:-2.8672em;\"><span class=\"pstrut\" style=\"height:3em;\"></span><span class=\"hide-tail\" style=\"min-width:0.853em;height:1.08em;\"><svg xmlns=\"http://www.w3.org/2000/svg\" width=\"400em\" height=\"1.08em\" viewBox=\"0 0 400000 1080\" preserveAspectRatio=\"xMinYMin slice\"><path d=\"M95,702\nc-2.7,0,-7.17,-2.7,-13.5,-8c-5.8,-5.3,-9.5,-10,-9.5,-14\nc0,-2,0.3,-3.3,1,-4c1.3,-2.7,23.83,-20.7,67.5,-54\nc44.2,-33.3,65.8,-50.3,66.5,-51c1.3,-1.3,3,-2,5,-2c4.7,0,8.7,3.3,12,10\ns173,378,173,378c0.7,0,35.3,-71,104,-213c68.7,-142,137.5,-285,206.5,-429\nc69,-144,104.5,-217.7,106.5,-221\nl0 -0\nc5.3,-9.3,12,-14,20,-14\nH400000v40H845.2724\ns-225.272,467,-225.272,467s-235,486,-235,486c-2.7,4.7,-9,7,-19,7\nc-6,0,-10,-1,-12,-3s-194,-422,-194,-422s-65,47,-65,47z\nM834 80h400000v40h-400000z\"/></svg></span></span></span><span class=\"vlist-s\">​</span></span><span class=\"vlist-r\"><span class=\"vlist\" style=\"height:0.1328em;\"><span></span></span></span></span></span><span class=\"mspace\" style=\"margin-right:0.1667em;\"></span><span class=\"mord mathnormal\" style=\"margin-right:0.03588em;\">σ</span></span></span><span style=\"top:-3.23em;\"><span class=\"pstrut\" style=\"height:3em;\"></span><span class=\"frac-line\" style=\"border-bottom-width:0.04em;\"></span></span><span style=\"top:-3.677em;\"><span class=\"pstrut\" style=\"height:3em;\"></span><span class=\"mord\"><span class=\"mord\">1</span></span></span></span><span class=\"vlist-s\">​</span></span><span class=\"vlist-r\"><span class=\"vlist\" style=\"height:0.93em;\"><span></span></span></span></span></span><span class=\"mclose nulldelimiter\"></span></span><span class=\"mord\"><span class=\"mord mathnormal\">e</span><span class=\"msupsub\"><span class=\"vlist-t\"><span class=\"vlist-r\"><span class=\"vlist\" style=\"height:1.3291em;\"><span style=\"top:-3.4534em;margin-right:0.05em;\"><span class=\"pstrut\" style=\"height:3em;\"></span><span class=\"sizing reset-size6 size3 mtight\"><span class=\"mord mtight\"><span class=\"mord mtight\">−</span><span class=\"mord mtight\"><span class=\"mopen nulldelimiter sizing reset-size3 size6\"></span><span class=\"mfrac\"><span class=\"vlist-t vlist-t2\"><span class=\"vlist-r\"><span class=\"vlist\" style=\"height:1.251em;\"><span style=\"top:-2.5062em;\"><span class=\"pstrut\" style=\"height:3em;\"></span><span class=\"sizing reset-size3 size1 mtight\"><span class=\"mord mtight\"><span class=\"mord mtight\">2</span><span class=\"mord mtight\"><span class=\"mord mathnormal mtight\" style=\"margin-right:0.03588em;\">σ</span><span class=\"msupsub\"><span class=\"vlist-t\"><span class=\"vlist-r\"><span class=\"vlist\" style=\"height:0.9384em;\"><span style=\"top:-2.9384em;margin-right:0.1em;\"><span class=\"pstrut\" style=\"height:2.6444em;\"></span><span class=\"mord mtight\">2</span></span></span></span></span></span></span></span></span></span><span style=\"top:-3.2255em;\"><span class=\"pstrut\" style=\"height:3em;\"></span><span class=\"frac-line mtight\" style=\"border-bottom-width:0.049em;\"></span></span><span style=\"top:-3.5021em;\"><span class=\"pstrut\" style=\"height:3em;\"></span><span class=\"sizing reset-size3 size1 mtight\"><span class=\"mord mtight\"><span class=\"mopen mtight\">(</span><span class=\"mord mathnormal mtight\">x</span><span class=\"mbin mtight\">−</span><span class=\"mord mathnormal mtight\">μ</span><span class=\"mclose mtight\"><span class=\"mclose mtight\">)</span><span class=\"msupsub\"><span class=\"vlist-t\"><span class=\"vlist-r\"><span class=\"vlist\" style=\"height:1.0484em;\"><span style=\"top:-3.0484em;margin-right:0.1em;\"><span class=\"pstrut\" style=\"height:2.6444em;\"></span><span class=\"mord mtight\">2</span></span></span></span></span></span></span></span></span></span></span><span class=\"vlist-s\">​</span></span><span class=\"vlist-r\"><span class=\"vlist\" style=\"height:0.4938em;\"><span></span></span></span></span></span><span class=\"mclose nulldelimiter sizing reset-size3 size6\"></span></span></span></span></span></span></span></span></span></span></span></span></span></span></p>\n<p>其分布函数为：</p>\n<p><span class=\"katex-display\"><span class=\"katex\"><span class=\"katex-mathml\"><math xmlns=\"http://www.w3.org/1998/Math/MathML\" display=\"block\"><semantics><mrow><mi>F</mi><mo stretchy=\"false\">(</mo><mi>x</mi><mo stretchy=\"false\">)</mo><mo>=</mo><msubsup><mo>∫</mo><mrow><mo>−</mo><mi mathvariant=\"normal\">∞</mi></mrow><mi>x</mi></msubsup><mfrac><mn>1</mn><mrow><msqrt><mrow><mn>2</mn><mi>π</mi></mrow></msqrt><mtext> </mtext><mi>σ</mi></mrow></mfrac><msup><mi>e</mi><mrow><mo>−</mo><mfrac><mrow><mo stretchy=\"false\">(</mo><mi>t</mi><mo>−</mo><mi>μ</mi><msup><mo stretchy=\"false\">)</mo><mn>2</mn></msup></mrow><mrow><mn>2</mn><msup><mi>σ</mi><mn>2</mn></msup></mrow></mfrac></mrow></msup><mtext> </mtext><mi>d</mi><mi>t</mi></mrow><annotation encoding=\"application/x-tex\">F(x) = \\int_{-\\infty}^{x} \\frac{1}{\\sqrt{2\\pi}\\,\\sigma} e^{-\\frac{(t - \\mu)^2}{2\\sigma^2}} \\, dt\n</annotation></semantics></math></span><span class=\"katex-html\" aria-hidden=\"true\"><span class=\"base\"><span class=\"strut\" style=\"height:1em;vertical-align:-0.25em;\"></span><span class=\"mord mathnormal\" style=\"margin-right:0.13889em;\">F</span><span class=\"mopen\">(</span><span class=\"mord mathnormal\">x</span><span class=\"mclose\">)</span><span class=\"mspace\" style=\"margin-right:0.2778em;\"></span><span class=\"mrel\">=</span><span class=\"mspace\" style=\"margin-right:0.2778em;\"></span></span><span class=\"base\"><span class=\"strut\" style=\"height:2.3846em;vertical-align:-0.9703em;\"></span><span class=\"mop\"><span class=\"mop op-symbol large-op\" style=\"margin-right:0.44445em;position:relative;top:-0.0011em;\">∫</span><span class=\"msupsub\"><span class=\"vlist-t vlist-t2\"><span class=\"vlist-r\"><span class=\"vlist\" style=\"height:1.4143em;\"><span style=\"top:-1.7881em;margin-left:-0.4445em;margin-right:0.05em;\"><span class=\"pstrut\" style=\"height:2.7em;\"></span><span class=\"sizing reset-size6 size3 mtight\"><span class=\"mord mtight\"><span class=\"mord mtight\">−</span><span class=\"mord mtight\">∞</span></span></span></span><span style=\"top:-3.8129em;margin-right:0.05em;\"><span class=\"pstrut\" style=\"height:2.7em;\"></span><span class=\"sizing reset-size6 size3 mtight\"><span class=\"mord mtight\"><span class=\"mord mathnormal mtight\">x</span></span></span></span></span><span class=\"vlist-s\">​</span></span><span class=\"vlist-r\"><span class=\"vlist\" style=\"height:0.9703em;\"><span></span></span></span></span></span></span><span class=\"mspace\" style=\"margin-right:0.1667em;\"></span><span class=\"mord\"><span class=\"mopen nulldelimiter\"></span><span class=\"mfrac\"><span class=\"vlist-t vlist-t2\"><span class=\"vlist-r\"><span class=\"vlist\" style=\"height:1.3214em;\"><span style=\"top:-2.2028em;\"><span class=\"pstrut\" style=\"height:3em;\"></span><span class=\"mord\"><span class=\"mord sqrt\"><span class=\"vlist-t vlist-t2\"><span class=\"vlist-r\"><span class=\"vlist\" style=\"height:0.9072em;\"><span class=\"svg-align\" style=\"top:-3em;\"><span class=\"pstrut\" style=\"height:3em;\"></span><span class=\"mord\" style=\"padding-left:0.833em;\"><span class=\"mord\">2</span><span class=\"mord mathnormal\" style=\"margin-right:0.03588em;\">π</span></span></span><span style=\"top:-2.8672em;\"><span class=\"pstrut\" style=\"height:3em;\"></span><span class=\"hide-tail\" style=\"min-width:0.853em;height:1.08em;\"><svg xmlns=\"http://www.w3.org/2000/svg\" width=\"400em\" height=\"1.08em\" viewBox=\"0 0 400000 1080\" preserveAspectRatio=\"xMinYMin slice\"><path d=\"M95,702\nc-2.7,0,-7.17,-2.7,-13.5,-8c-5.8,-5.3,-9.5,-10,-9.5,-14\nc0,-2,0.3,-3.3,1,-4c1.3,-2.7,23.83,-20.7,67.5,-54\nc44.2,-33.3,65.8,-50.3,66.5,-51c1.3,-1.3,3,-2,5,-2c4.7,0,8.7,3.3,12,10\ns173,378,173,378c0.7,0,35.3,-71,104,-213c68.7,-142,137.5,-285,206.5,-429\nc69,-144,104.5,-217.7,106.5,-221\nl0 -0\nc5.3,-9.3,12,-14,20,-14\nH400000v40H845.2724\ns-225.272,467,-225.272,467s-235,486,-235,486c-2.7,4.7,-9,7,-19,7\nc-6,0,-10,-1,-12,-3s-194,-422,-194,-422s-65,47,-65,47z\nM834 80h400000v40h-400000z\"/></svg></span></span></span><span class=\"vlist-s\">​</span></span><span class=\"vlist-r\"><span class=\"vlist\" style=\"height:0.1328em;\"><span></span></span></span></span></span><span class=\"mspace\" style=\"margin-right:0.1667em;\"></span><span class=\"mord mathnormal\" style=\"margin-right:0.03588em;\">σ</span></span></span><span style=\"top:-3.23em;\"><span class=\"pstrut\" style=\"height:3em;\"></span><span class=\"frac-line\" style=\"border-bottom-width:0.04em;\"></span></span><span style=\"top:-3.677em;\"><span class=\"pstrut\" style=\"height:3em;\"></span><span class=\"mord\"><span class=\"mord\">1</span></span></span></span><span class=\"vlist-s\">​</span></span><span class=\"vlist-r\"><span class=\"vlist\" style=\"height:0.93em;\"><span></span></span></span></span></span><span class=\"mclose nulldelimiter\"></span></span><span class=\"mord\"><span class=\"mord mathnormal\">e</span><span class=\"msupsub\"><span class=\"vlist-t\"><span class=\"vlist-r\"><span class=\"vlist\" style=\"height:1.3291em;\"><span style=\"top:-3.4534em;margin-right:0.05em;\"><span class=\"pstrut\" style=\"height:3em;\"></span><span class=\"sizing reset-size6 size3 mtight\"><span class=\"mord mtight\"><span class=\"mord mtight\">−</span><span class=\"mord mtight\"><span class=\"mopen nulldelimiter sizing reset-size3 size6\"></span><span class=\"mfrac\"><span class=\"vlist-t vlist-t2\"><span class=\"vlist-r\"><span class=\"vlist\" style=\"height:1.251em;\"><span style=\"top:-2.5062em;\"><span class=\"pstrut\" style=\"height:3em;\"></span><span class=\"sizing reset-size3 size1 mtight\"><span class=\"mord mtight\"><span class=\"mord mtight\">2</span><span class=\"mord mtight\"><span class=\"mord mathnormal mtight\" style=\"margin-right:0.03588em;\">σ</span><span class=\"msupsub\"><span class=\"vlist-t\"><span class=\"vlist-r\"><span class=\"vlist\" style=\"height:0.9384em;\"><span style=\"top:-2.9384em;margin-right:0.1em;\"><span class=\"pstrut\" style=\"height:2.6444em;\"></span><span class=\"mord mtight\">2</span></span></span></span></span></span></span></span></span></span><span style=\"top:-3.2255em;\"><span class=\"pstrut\" style=\"height:3em;\"></span><span class=\"frac-line mtight\" style=\"border-bottom-width:0.049em;\"></span></span><span style=\"top:-3.5021em;\"><span class=\"pstrut\" style=\"height:3em;\"></span><span class=\"sizing reset-size3 size1 mtight\"><span class=\"mord mtight\"><span class=\"mopen mtight\">(</span><span class=\"mord mathnormal mtight\">t</span><span class=\"mbin mtight\">−</span><span class=\"mord mathnormal mtight\">μ</span><span class=\"mclose mtight\"><span class=\"mclose mtight\">)</span><span class=\"msupsub\"><span class=\"vlist-t\"><span class=\"vlist-r\"><span class=\"vlist\" style=\"height:1.0484em;\"><span style=\"top:-3.0484em;margin-right:0.1em;\"><span class=\"pstrut\" style=\"height:2.6444em;\"></span><span class=\"mord mtight\">2</span></span></span></span></span></span></span></span></span></span></span><span class=\"vlist-s\">​</span></span><span class=\"vlist-r\"><span class=\"vlist\" style=\"height:0.4938em;\"><span></span></span></span></span></span><span class=\"mclose nulldelimiter sizing reset-size3 size6\"></span></span></span></span></span></span></span></span></span></span><span class=\"mspace\" style=\"margin-right:0.1667em;\"></span><span class=\"mord mathnormal\">d</span><span class=\"mord mathnormal\">t</span></span></span></span></span></p>\n<p>分别使用全国万强、全国千强、全国百强的平均巅峰分数代入x，结合μ值以及玩家占比，求解得到 σ。值得注意的是，因为每条分路均有足量的玩家，分布玩家总数量分别为50000、5000、500，而不是10000、1000、100与玩家总人数做比。</p>\n<h4 id=\"2-2-4-数学模型验证\">2.2.4 数学模型验证</h4>\n<p>共得到3个模型，每个模型使用未参与构建的另外三个巅峰分与占比进行检验。即将另外三个分路排名的平均巅峰分代入后，得到这三个分路排名玩家的占比，与真实占比进行比较，选取预测和实际值最接近的模型作为本研究最终结果。</p>\n<h3 id=\"2-3-计算高端局对应的巅峰分数\">2.3 计算高端局对应的巅峰分数</h3>\n<p>本质上，与高端局对应的是普通对局，普通对局又可以理解为常见对局。根据统计学原理，(95%) 的玩家所处的对局为“正常对局”，高端局可以被看成低概率出现的“异常对局”。因此使用最优的分布模型，依次代入 (F(x) = 0.95)、(0.975)、(0.99)、(0.999)，解出的 (x) 值（四舍五入处理）就是对应该玩家已经超越了全王者人员 (95%)、(97.5%)、(99%)、(99.9%) 的玩家，其所处的对局就是王者荣耀数学意义上的高端局，即前 (5%)、(2.5%)、(1%)、(0.1%) 的对局。</p>\n<p>使用Python进行本研究全部复杂计算与绘图。</p>\n<h3 id=\"2-4-赛季不同时段高端局判断方法\">2.4 赛季不同时段高端局判断方法</h3>\n<p>众所周知，随着玩家的胜败，赛季初与赛季末的巅峰赛分数不同，因此对应的高端局判定标准也必然不一致。在这里，作者结合上述研究成果，开发出一个Python算法，玩家可以通过输入实时的巅峰第一分数与巅峰万强分数，计算此时王者荣耀高端局对应的占比。</p>\n<h2 id=\"3-结果与讨论\">3 结果与讨论</h2>\n<h3 id=\"3-1-各数学模型计算与检验结果\">3.1 各数学模型计算与检验结果</h3>\n<p>图1表明，使用巅峰万强为输入数据的模型效果最好。</p>\n<p><img src=\"https://img.rubbish.press/file/2604/1775660622597_image.png\" alt=\"\"></p>\n<center>图1 三个模型构建后，使用未参与构建的指标进行检验的预测值与实际值对比，其中a、b、c图分别为使用巅峰万强、巅峰千强、巅峰百强数据构建</center>\n<h3 id=\"3-2-高端局对应巅峰分\">3.2 高端局对应巅峰分</h3>\n<p>经计算，前 (5%)、(2.5%)、(1%)、(0.1%) 的对局对应的巅峰分依次为1549、1671、1812、2106（图2）。因此，只要玩家的巅峰赛分数达到1549分及以上，就可以认为该玩家已经跨入“高端局”的门槛；如果该玩家巅峰分数达到1812分及以上，那么这位玩家的实力已经超越全王者人员 (99%) 的玩家；如果一位玩家的巅峰分数达到2106分及以上，那么可以认为，1000名王者荣耀玩家中，才会有1名这样的玩家。</p>\n<p><img src=\"https://img.rubbish.press/file/2604/1775660644485_image.png\" alt=\"\"></p>\n<center>图2 赛季末巅峰分数与低于对应巅峰分玩家占比的关系，图像上的点表示前 5%、2.5%、1%、0.1%的对局对应的巅峰分</center>\n<h3 id=\"3-3-不同时段的高端局衡量方法\">3.3 不同时段的高端局衡量方法</h3>\n<p>本研究使用的所有代码，以及开发用于实时确定高端局的Python算法可以在 <a href=\"https://gitee.com/wys477474310/avz/tree/master/\">https://gitee.com/wys477474310/avz/tree/master/</a> 获取。</p>\n<h2 id=\"4-结论\">4 结论</h2>\n<p>本研究指出，前 (5%)、(2.5%)、(1%)、(0.1%) 的对局对应的巅峰分依次为1549、1671、1812、2106。因此，只要达到以上这些分数，你就拥有了在网络上炫耀的资本。如果有人质疑，你就将这篇论文糊在他的脸上，让他去发表反驳我的论文。</p>\n<h2 id=\"声明\">声明</h2>\n<p>由于作者不是计算机专业，因此没有实力将该算法包装为小软件或小程序。不过如果有高技术人才能做到这一点，希望你在软件或程序中，加入本人或本论文的引用信息。如果希望指出错误或能改进的地方，请看作者下面的那个邮箱，可以联系到我，但我基本不登录QQ，所以能否回复、是否有时间改进，都是问题。</p>\n<h2 id=\"致谢\">致谢</h2>\n<p>感谢我的两位室友带我入坑王者荣耀，没有说我室友不好的意思，但是可能我上辈子作恶多端，这辈子玩到了王者荣耀这个游戏。</p>\n<h2 id=\"参考文献\">参考文献</h2>\n<p>[1] 陈海遥王者教学. 【王者数据科普】什么是高分段，梯度要怎么看？. bilibili. <a href=\"https://www.bilibili.com/video/BV1VHkwBNE6p\">https://www.bilibili.com/video/BV1VHkwBNE6p</a>.</p>\n<p>[2] 韩云青不涨粉. 聊一下多少分算高手. bilibili. <a href=\"https://www.bilibili.com/video/BV17JsmzGEgo\">https://www.bilibili.com/video/BV17JsmzGEgo</a>.</p>\n<p>[3] 困境王者导师. 王者荣耀实力层级划分，一期视频让你真正了解各个分段的含金量（各个分段的突破方法）. bilibili. <a href=\"https://www.bilibili.com/video/BV1KDWFzQENc\">https://www.bilibili.com/video/BV1KDWFzQENc</a>.</p>\n<p>[4] 王者荣耀. #王者荣耀2025年国服日活用户数突破1.39亿#. bilibili. <a href=\"https://www.bilibili.com/opus/1128016960652574742\">https://www.bilibili.com/opus/1128016960652574742</a></p>\n","categories":[{"name":"文章","path":"api/categories/文章.json"},{"name":"实用","path":"api/categories/实用.json"}],"tags":[{"name":"王者荣耀","path":"api/tags/王者荣耀.json"},{"name":"高端局","path":"api/tags/高端局.json"},{"name":"正态分布","path":"api/tags/正态分布.json"},{"name":"巅峰赛","path":"api/tags/巅峰赛.json"},{"name":"Python","path":"api/tags/Python.json"}]}