{"name":"电竞文化","postlist":[{"title":"隔音棚失语症(SBA)：技术隔离对嘲讽型选手的“声学阉割” ——基于对 DOTA 职业选手的观察","slug":"隔音棚失语症(SBA)：技术隔离对嘲讽型选手的“声学阉割” ——基于对 DOTA 职业选手的观察","date":"2026-04-19T05:34:06.337Z","updated":"2026-04-19T06:02:29.434Z","comments":true,"path":"api/articles/隔音棚失语症(SBA)：技术隔离对嘲讽型选手的“声学阉割” ——基于对 DOTA 职业选手的观察.json","excerpt":null,"keywords":null,"cover":"https://img.rubbish.press/file/2604/1776577011836_bfa2bbd11380ab48c67585ee55500b2f.png","content":null,"raw":null,"categories":[{"name":"文章","path":"api/categories/文章.json"},{"name":"实用","path":"api/categories/实用.json"}],"tags":[{"name":"隔音棚","path":"api/tags/隔音棚.json"},{"name":"失语症","path":"api/tags/失语症.json"},{"name":"嘲讽型选手","path":"api/tags/嘲讽型选手.json"},{"name":"电竞文化","path":"api/tags/电竞文化.json"},{"name":"Dota","path":"api/tags/Dota.json"}]}]}