{"name":"睡眠锭子","postlist":[{"title":"生命因何而沉睡——论睡前听书如何更加连贯","slug":"生命因何而沉睡——论睡前听书如何更加连贯","date":"2026-04-20T15:52:40.740Z","updated":"2026-04-20T16:00:58.969Z","comments":true,"path":"api/articles/生命因何而沉睡——论睡前听书如何更加连贯.json","excerpt":null,"keywords":null,"cover":"https://img.rubbish.press/file/2604/1776700479913_睡觉.png","content":null,"raw":null,"categories":[{"name":"文章","path":"api/categories/文章.json"},{"name":"脑洞","path":"api/categories/脑洞.json"}],"tags":[{"name":"海马体","path":"api/tags/海马体.json"},{"name":"听书入睡","path":"api/tags/听书入睡.json"},{"name":"睡眠锭子","path":"api/tags/睡眠锭子.json"},{"name":"逆行性遗忘","path":"api/tags/逆行性遗忘.json"},{"name":"观测者悖论","path":"api/tags/观测者悖论.json"}]}]}